README.md
setup.py
juqcs/__init__.py
juqcs/authentication.py
juqcs/backend.py
juqcs/client.py
juqcs/exceptions.py
juqcs/job.py
juqcs/provider.py
qiskit_juqcs.egg-info/PKG-INFO
qiskit_juqcs.egg-info/SOURCES.txt
qiskit_juqcs.egg-info/dependency_links.txt
qiskit_juqcs.egg-info/not-zip-safe
qiskit_juqcs.egg-info/requires.txt
qiskit_juqcs.egg-info/top_level.txt
test/test.py