Metadata-Version: 2.1
Name: qiskit-juqcs
Version: 0.4.0
Summary: Qiskit provider for JUQCS (Juelich Universal Quantum Computer Simulator)
Home-page: https://jugit.fz-juelich.de/qip/juniq-platform/qiskit-juqcs
Author: Carlos Gonzalez
Author-email: c.gonzalez.calaza@fz-juelich.de
License: MIT
Platform: UNKNOWN
Classifier: License :: OSI Approved :: MIT License
Classifier: Programming Language :: Python :: 3
